ST7735/__init__.py
ST7735-0.0.5.dist-info/LICENSE.txt
ST7735-0.0.5.dist-info/METADATA
ST7735-0.0.5.dist-info/WHEEL
ST7735-0.0.5.dist-info/top_level.txt
ST7735-0.0.5.dist-info/RECORD
